devgenius/README.md
devgenius/__init__.py
devgenius/api_client.py
devgenius/mcp_server.py
devgenius/rules_manager.py
devgenius/tools_registry.py
devgenius_mcp_client.py
devgenius_mcp_client-1.3.7.dist-info/METADATA
devgenius_mcp_client-1.3.7.dist-info/WHEEL
devgenius_mcp_client-1.3.7.dist-info/entry_points.txt
devgenius_mcp_client-1.3.7.dist-info/RECORD
