Metadata-Version: 2.4
Name: devgenius-mcp-client
Version: 1.3.7
Summary: DevGenius MCP Client for AI IDEs
Requires-Python: >=3.8
Requires-Dist: httpx>=0.26.0
